autopoputils/__init__.py
autopoputils/aws_util.py
autopoputils/recording_util.py
autopoputils-1.0.dist-info/METADATA
autopoputils-1.0.dist-info/WHEEL
autopoputils-1.0.dist-info/top_level.txt
autopoputils-1.0.dist-info/RECORD
