Metadata-Version: 2.1
Name: autopoputils
Version: 1.0
Summary: Auto Populate GDoc tables using LLMs Utilities.
Home-page: https://github.com/yourusername/yourrepository
Author: David Schwartz
Author-email: david.schwartz@devfactory.com
License: UNKNOWN
Platform: UNKNOWN
Classifier: Programming Language :: Python :: 3
Classifier: License :: OSI Approved :: MIT License
Classifier: Operating System :: OS Independent
Requires-Dist: boto3
Requires-Dist: requests
Requires-Dist: selenium
